djcelery_model/__init__.py
djcelery_model/models.py
djcelery_model/migrations/0001_initial.py
djcelery_model/migrations/0002_auto_20190125_1008.py
djcelery_model/migrations/__init__.py
djcelery_model/south_migrations/0001_initial.py
djcelery_model/south_migrations/0002_auto__add_field_modeltaskmeta_state.py
djcelery_model/south_migrations/__init__.py
django_celery_model-0.2.1.dist-info/COPYING
django_celery_model-0.2.1.dist-info/METADATA
django_celery_model-0.2.1.dist-info/WHEEL
django_celery_model-0.2.1.dist-info/top_level.txt
django_celery_model-0.2.1.dist-info/RECORD
