Metadata-Version: 2.1
Name: django-celery-model
Version: 0.2.1
Summary: django-celery-model is an extension to Celery which adds support for tracking Celery tasks assigned to Django model instances.
Home-page: https://github.com/mback2k/django-celery-model
Author: Marc Hoersken
Author-email: info@marc-hoersken.de
License: MIT
Platform: UNKNOWN
Classifier: Topic :: Internet :: WWW/HTTP :: Dynamic Content
Classifier: Intended Audience :: Developers
Classifier: License :: OSI Approved :: MIT License
Classifier: Programming Language :: Python
Classifier: Topic :: Software Development :: Libraries :: Python Modules
Classifier: Development Status :: 4 - Beta
Classifier: Operating System :: OS Independent
Requires-Dist: django (>=1.11)
Requires-Dist: celery (>=4.2)
